{"id":"1.13","label":"Removing Discontinuities","questions":[{"id":"CALCT3BC-P00066-Q0001","source_object_id":"4F855D45C74545D295D31FDF45C24809","bank_code":"CALCT3BC","pool_id":"00066","pool_uid":"CALCT3BC:00066","pool_title":"Chapter 002 - Instructor Test Items - 2.6  Continuity - 7  Find Constants that Make a Function Continuous at Point","bank":{"code":"CALCT3BC","title":"Calculus: Early Transcendentals, 3e","authors":"Briggs, Cochran, Gillett, Schulz","edition":"3e","isbn":"9780134770529","resource_isbn":"9780134770529","format":"Pearson TestGen Blackboard QTI pool export"},"source":{"chapter":2,"chapter_title":"","section":"2.6","section_title":"Continuity","skill_number":7,"skill_title":"Find Constants that Make a Function Continuous at Point","publisher_format":"Pearson TestGen Blackboard QTI pool export","original_question_number":1},"classification":{"ap_unit":1,"ap_unit_label":"Limits and Continuity","ap_topic":"1.13","ap_topic_title":"Removing Discontinuities","ap_scope":"ab_bc","course_scope":"AP Calculus AB/BC","alignment_confidence":"high","alignment_basis":"source_skill","crosswalk_status":"preliminary_question_level","crosswalk_note":"","framework":"AP Calculus Course and Exam Description, current Unit 1 topic framework"},"type":"mcq","prompt_html":"<span style=\"font-weight: bold;\">Find numbers a and b, or k, so that f is continuous at every point.<br/><br/><br/></span><img alt=\"f(x) = \" class=\"question-media\" decoding=\"async\" loading=\"lazy\" src=\"assets/calct3bc/ppg/calct3bcbb0805202334/f66g1q1g1.jpg\" style=\"vertical-align: -4.0px;\"/><img alt=\"{ -2, ax + b,  2,\" class=\"question-media\" decoding=\"async\" loading=\"lazy\" src=\"assets/calct3bc/ppg/calct3bcbb0805202334/f66g1q1g2.jpg\" style=\"vertical-align: -4.0px;\"/>  <img alt=\"x &lt; -5-5 ≤ x ≤ -3x &gt; -3\" class=\"question-media\" decoding=\"async\" loading=\"lazy\" src=\"assets/calct3bc/ppg/calct3bcbb0805202334/f66g1q1g3.jpg\" style=\"vertical-align: -4.0px;\"/>","prompt_text":"Find numbers a and b, or k, so that f is continuous at every point. f(x) = { -2, ax + b, 2, x < -5-5 ≤ x ≤ -3x > -3","choices":[{"id":"8A60020AD2E2453C83924034398A907C","label":"A","html":"a = -2, b = 2","text":"a = -2, b = 2"},{"id":"505933BEB28544AEA2853B65DD82739E","label":"B","html":"a = 2, b = 8","text":"a = 2, b = 8"},{"id":"0D2BB834B645490BB833B282B62AEB98","label":"C","html":"a = 2, b = -4","text":"a = 2, b = -4"},{"id":"F3D95FE8328E4F80B28980D04219B3A4","label":"D","html":"Impossible","text":"Impossible"}],"correct_choice_ids":["505933BEB28544AEA2853B65DD82739E"],"correct_choice_indices":[1],"accepted_answers":[],"solution_html":"","solution_text":"","feedback_html":{},"images":[{"src":"assets/calct3bc/ppg/calct3bcbb0805202334/f66g1q1g1.jpg","alt":"f(x) = "},{"src":"assets/calct3bc/ppg/calct3bcbb0805202334/f66g1q1g2.jpg","alt":"{ -2, ax + b,  2,"},{"src":"assets/calct3bc/ppg/calct3bcbb0805202334/f66g1q1g3.jpg","alt":"x < -5-5 ≤ x ≤ -3x > -3"}],"metadata":{"source_difficulty":"School","difficulty":null,"calculator":null,"estimated_seconds":90,"shuffle_choices":false,"review_status":"imported_unreviewed","math_format":"publisher_images_and_html"}},{"id":"CALCT3BC-P00066-Q0002","source_object_id":"B4AF72B221534D7D94BB88FE58EE7703","bank_code":"CALCT3BC","pool_id":"00066","pool_uid":"CALCT3BC:00066","pool_title":"Chapter 002 - Instructor Test Items - 2.6  Continuity - 7  Find Constants that Make a Function Continuous at Point","bank":{"code":"CALCT3BC","title":"Calculus: Early Transcendentals, 3e","authors":"Briggs, Cochran, Gillett, Schulz","edition":"3e","isbn":"9780134770529","resource_isbn":"9780134770529","format":"Pearson TestGen Blackboard QTI pool export"},"source":{"chapter":2,"chapter_title":"","section":"2.6","section_title":"Continuity","skill_number":7,"skill_title":"Find Constants that Make a Function Continuous at Point","publisher_format":"Pearson TestGen Blackboard QTI pool export","original_question_number":2},"classification":{"ap_unit":1,"ap_unit_label":"Limits and Continuity","ap_topic":"1.13","ap_topic_title":"Removing Discontinuities","ap_scope":"ab_bc","course_scope":"AP Calculus AB/BC","alignment_confidence":"high","alignment_basis":"source_skill","crosswalk_status":"preliminary_question_level","crosswalk_note":"","framework":"AP Calculus Course and Exam Description, current Unit 1 topic framework"},"type":"mcq","prompt_html":"<span style=\"font-weight: bold;\">Find numbers a and b, or k, so that f is continuous at every point.<br/><br/><br/></span><img alt=\" f(x) = \" class=\"question-media\" decoding=\"async\" loading=\"lazy\" src=\"assets/calct3bc/ppg/calct3bcbb0805202334/f66g1q2g1.jpg\" style=\"vertical-align: -4.0px;\"/><img alt=\"{ x2, ax + b, x + 20,\" class=\"question-media\" decoding=\"async\" loading=\"lazy\" src=\"assets/calct3bc/ppg/calct3bcbb0805202334/f66g1q2g2.jpg\" style=\"vertical-align: -4.0px;\"/> <img alt=\"x &lt; -5-5 ≤ x ≤ -4x &gt; -4\" class=\"question-media\" decoding=\"async\" loading=\"lazy\" src=\"assets/calct3bc/ppg/calct3bcbb0805202334/f66g1q2g3.jpg\" style=\"vertical-align: -4.0px;\"/>","prompt_text":"Find numbers a and b, or k, so that f is continuous at every point. f(x) = { x2, ax + b, x + 20, x < -5-5 ≤ x ≤ -4x > -4","choices":[{"id":"F638FB95852A47CF9A99D8356B06451B","label":"A","html":"a = -9, b = 20","text":"a = -9, b = 20"},{"id":"90C665DA8CD9416CAB64A960E025C417","label":"B","html":"a = 9, b = -20","text":"a = 9, b = -20"},{"id":"B38BF185D30A4A06B055FC60E4529D53","label":"C","html":"a = -9, b = -20","text":"a = -9, b = -20"},{"id":"96C1E4EC084D4DF38B478A13F769CFD3","label":"D","html":"Impossible","text":"Impossible"}],"correct_choice_ids":["B38BF185D30A4A06B055FC60E4529D53"],"correct_choice_indices":[2],"accepted_answers":[],"solution_html":"","solution_text":"","feedback_html":{},"images":[{"src":"assets/calct3bc/ppg/calct3bcbb0805202334/f66g1q2g1.jpg","alt":" f(x) = "},{"src":"assets/calct3bc/ppg/calct3bcbb0805202334/f66g1q2g2.jpg","alt":"{ x2, ax + b, x + 20,"},{"src":"assets/calct3bc/ppg/calct3bcbb0805202334/f66g1q2g3.jpg","alt":"x < -5-5 ≤ x ≤ -4x > -4"}],"metadata":{"source_difficulty":"School","difficulty":null,"calculator":null,"estimated_seconds":90,"shuffle_choices":false,"review_status":"imported_unreviewed","math_format":"publisher_images_and_html"}},{"id":"CALCT3BC-P00066-Q0003","source_object_id":"9C6C44C5229C4B4199DC0FE2C0C2530B","bank_code":"CALCT3BC","pool_id":"00066","pool_uid":"CALCT3BC:00066","pool_title":"Chapter 002 - Instructor Test Items - 2.6  Continuity - 7  Find Constants that Make a Function Continuous at Point","bank":{"code":"CALCT3BC","title":"Calculus: Early Transcendentals, 3e","authors":"Briggs, Cochran, Gillett, Schulz","edition":"3e","isbn":"9780134770529","resource_isbn":"9780134770529","format":"Pearson TestGen Blackboard QTI pool export"},"source":{"chapter":2,"chapter_title":"","section":"2.6","section_title":"Continuity","skill_number":7,"skill_title":"Find Constants that Make a Function Continuous at Point","publisher_format":"Pearson TestGen Blackboard QTI pool export","original_question_number":3},"classification":{"ap_unit":1,"ap_unit_label":"Limits and Continuity","ap_topic":"1.13","ap_topic_title":"Removing Discontinuities","ap_scope":"ab_bc","course_scope":"AP Calculus AB/BC","alignment_confidence":"high","alignment_basis":"source_skill","crosswalk_status":"preliminary_question_level","crosswalk_note":"","framework":"AP Calculus Course and Exam Description, current Unit 1 topic framework"},"type":"mcq","prompt_html":"<span style=\"font-weight: bold;\">Find numbers a and b, or k, so that f is continuous at every point.<br/><br/><br/></span><img alt=\"  f(x) =  \" class=\"question-media\" decoding=\"async\" loading=\"lazy\" src=\"assets/calct3bc/ppg/calct3bcbb0805202334/f66g1q3g1.jpg\" style=\"vertical-align: -4.0px;\"/><img alt=\"{ 7x + 10, kx + 6,\" class=\"question-media\" decoding=\"async\" loading=\"lazy\" src=\"assets/calct3bc/ppg/calct3bcbb0805202334/f66g1q3g2.jpg\" style=\"vertical-align: -4.0px;\"/> <img alt=\"if x &lt; -5if x ≥ -5\" class=\"question-media\" decoding=\"async\" loading=\"lazy\" src=\"assets/calct3bc/ppg/calct3bcbb0805202334/f66g1q3g3.jpg\" style=\"vertical-align: -4.0px;\"/>","prompt_text":"Find numbers a and b, or k, so that f is continuous at every point. f(x) = { 7x + 10, kx + 6, if x < -5if x ≥ -5","choices":[{"id":"2BFB31297A8742F591BD98F553B012B6","label":"A","html":"k = 11","text":"k = 11"},{"id":"5068248EEC47486AA08E08E3FA9A8F02","label":"B","html":"k = <img alt=\"(31/5)\" class=\"question-media\" decoding=\"async\" loading=\"lazy\" src=\"assets/calct3bc/ppg/calct3bcbb0805202334/f66g1q3g4.jpg\" style=\"vertical-align: -17.0px;\"/>","text":"k = (31/5)"},{"id":"96F89A49E12244B9B57FAC4F86488E26","label":"C","html":"k = <img alt=\"(6/5)\" class=\"question-media\" decoding=\"async\" loading=\"lazy\" src=\"assets/calct3bc/ppg/calct3bcbb0805202334/f66g1q3g5.jpg\" style=\"vertical-align: -17.0px;\"/>","text":"k = (6/5)"},{"id":"1AB8FBBD876F4CE9B1859DE1CC699801","label":"D","html":"k = - <img alt=\"(6/5)\" class=\"question-media\" decoding=\"async\" loading=\"lazy\" src=\"assets/calct3bc/ppg/calct3bcbb0805202334/f66g1q3g6.jpg\" style=\"vertical-align: -17.0px;\"/>","text":"k = - (6/5)"}],"correct_choice_ids":["5068248EEC47486AA08E08E3FA9A8F02"],"correct_choice_indices":[1],"accepted_answers":[],"solution_html":"","solution_text":"","feedback_html":{},"images":[{"src":"assets/calct3bc/ppg/calct3bcbb0805202334/f66g1q3g1.jpg","alt":"  f(x) =  "},{"src":"assets/calct3bc/ppg/calct3bcbb0805202334/f66g1q3g2.jpg","alt":"{ 7x + 10, kx + 6,"},{"src":"assets/calct3bc/ppg/calct3bcbb0805202334/f66g1q3g3.jpg","alt":"if x < -5if x ≥ -5"},{"src":"assets/calct3bc/ppg/calct3bcbb0805202334/f66g1q3g4.jpg","alt":"(31/5)"},{"src":"assets/calct3bc/ppg/calct3bcbb0805202334/f66g1q3g5.jpg","alt":"(6/5)"},{"src":"assets/calct3bc/ppg/calct3bcbb0805202334/f66g1q3g6.jpg","alt":"(6/5)"}],"metadata":{"source_difficulty":"School","difficulty":null,"calculator":null,"estimated_seconds":90,"shuffle_choices":true,"review_status":"imported_unreviewed","math_format":"publisher_images_and_html"}},{"id":"CALCT3BC-P00066-Q0004","source_object_id":"C40B9A03C39A444E8CC21F1A288AF592","bank_code":"CALCT3BC","pool_id":"00066","pool_uid":"CALCT3BC:00066","pool_title":"Chapter 002 - Instructor Test Items - 2.6  Continuity - 7  Find Constants that Make a Function Continuous at Point","bank":{"code":"CALCT3BC","title":"Calculus: Early Transcendentals, 3e","authors":"Briggs, Cochran, Gillett, Schulz","edition":"3e","isbn":"9780134770529","resource_isbn":"9780134770529","format":"Pearson TestGen Blackboard QTI pool export"},"source":{"chapter":2,"chapter_title":"","section":"2.6","section_title":"Continuity","skill_number":7,"skill_title":"Find Constants that Make a Function Continuous at Point","publisher_format":"Pearson TestGen Blackboard QTI pool export","original_question_number":4},"classification":{"ap_unit":1,"ap_unit_label":"Limits and Continuity","ap_topic":"1.13","ap_topic_title":"Removing Discontinuities","ap_scope":"ab_bc","course_scope":"AP Calculus AB/BC","alignment_confidence":"high","alignment_basis":"source_skill","crosswalk_status":"preliminary_question_level","crosswalk_note":"","framework":"AP Calculus Course and Exam Description, current Unit 1 topic framework"},"type":"mcq","prompt_html":"<span style=\"font-weight: bold;\">Find numbers a and b, or k, so that f is continuous at every point.<br/><br/><br/></span><img alt=\"  f(x) =  \" class=\"question-media\" decoding=\"async\" loading=\"lazy\" src=\"assets/calct3bc/ppg/calct3bcbb0805202334/f66g1q4g1.jpg\" style=\"vertical-align: -4.0px;\"/><img alt=\"{ (x) with superscript (2), x + k,\" class=\"question-media\" decoding=\"async\" loading=\"lazy\" src=\"assets/calct3bc/ppg/calct3bcbb0805202334/f66g1q4g2.jpg\" style=\"vertical-align: -4.0px;\"/> <img alt=\"if x ≤ 4if x &gt; 4\" class=\"question-media\" decoding=\"async\" loading=\"lazy\" src=\"assets/calct3bc/ppg/calct3bcbb0805202334/f66g1q4g3.jpg\" style=\"vertical-align: -4.0px;\"/>","prompt_text":"Find numbers a and b, or k, so that f is continuous at every point. f(x) = { (x) with superscript (2), x + k, if x ≤ 4if x > 4","choices":[{"id":"23806FF359254851A8EADAA019C82000","label":"A","html":"k = -4","text":"k = -4"},{"id":"D3267D7E2F6C42A9BEF795ED3357E04B","label":"B","html":"k = 20","text":"k = 20"},{"id":"8427DC41432940A6AE6BF9068D63D130","label":"C","html":"k = 12","text":"k = 12"},{"id":"148F978615B54FDCA45FF1552AA4F412","label":"D","html":"Impossible","text":"Impossible"}],"correct_choice_ids":["8427DC41432940A6AE6BF9068D63D130"],"correct_choice_indices":[2],"accepted_answers":[],"solution_html":"","solution_text":"","feedback_html":{},"images":[{"src":"assets/calct3bc/ppg/calct3bcbb0805202334/f66g1q4g1.jpg","alt":"  f(x) =  "},{"src":"assets/calct3bc/ppg/calct3bcbb0805202334/f66g1q4g2.jpg","alt":"{ (x) with superscript (2), x + k,"},{"src":"assets/calct3bc/ppg/calct3bcbb0805202334/f66g1q4g3.jpg","alt":"if x ≤ 4if x > 4"}],"metadata":{"source_difficulty":"School","difficulty":null,"calculator":null,"estimated_seconds":90,"shuffle_choices":false,"review_status":"imported_unreviewed","math_format":"publisher_images_and_html"}},{"id":"CALCT3BC-P00066-Q0005","source_object_id":"6FE24546043143BF8E1BA7B452F754FD","bank_code":"CALCT3BC","pool_id":"00066","pool_uid":"CALCT3BC:00066","pool_title":"Chapter 002 - Instructor Test Items - 2.6  Continuity - 7  Find Constants that Make a Function Continuous at Point","bank":{"code":"CALCT3BC","title":"Calculus: Early Transcendentals, 3e","authors":"Briggs, Cochran, Gillett, Schulz","edition":"3e","isbn":"9780134770529","resource_isbn":"9780134770529","format":"Pearson TestGen Blackboard QTI pool export"},"source":{"chapter":2,"chapter_title":"","section":"2.6","section_title":"Continuity","skill_number":7,"skill_title":"Find Constants that Make a Function Continuous at Point","publisher_format":"Pearson TestGen Blackboard QTI pool export","original_question_number":5},"classification":{"ap_unit":1,"ap_unit_label":"Limits and Continuity","ap_topic":"1.13","ap_topic_title":"Removing Discontinuities","ap_scope":"ab_bc","course_scope":"AP Calculus AB/BC","alignment_confidence":"high","alignment_basis":"source_skill","crosswalk_status":"preliminary_question_level","crosswalk_note":"","framework":"AP Calculus Course and Exam Description, current Unit 1 topic framework"},"type":"mcq","prompt_html":"<span style=\"font-weight: bold;\">Find numbers a and b, or k, so that f is continuous at every point.<br/><br/><br/></span><img alt=\"  f(x) =  \" class=\"question-media\" decoding=\"async\" loading=\"lazy\" src=\"assets/calct3bc/ppg/calct3bcbb0805202334/f66g1q5g1.jpg\" style=\"vertical-align: -4.0px;\"/><img alt=\"{ (x) with superscript (2), kx,\" class=\"question-media\" decoding=\"async\" loading=\"lazy\" src=\"assets/calct3bc/ppg/calct3bcbb0805202334/f66g1q5g2.jpg\" style=\"vertical-align: -4.0px;\"/>  <img alt=\"if x ≤ 4if x &gt; 4\" class=\"question-media\" decoding=\"async\" loading=\"lazy\" src=\"assets/calct3bc/ppg/calct3bcbb0805202334/f66g1q5g3.jpg\" style=\"vertical-align: -4.0px;\"/>","prompt_text":"Find numbers a and b, or k, so that f is continuous at every point. f(x) = { (x) with superscript (2), kx, if x ≤ 4if x > 4","choices":[{"id":"74EA0C619EDC404582A94CA0F019130A","label":"A","html":"k = <img alt=\"(1/4)\" class=\"question-media\" decoding=\"async\" loading=\"lazy\" src=\"assets/calct3bc/ppg/calct3bcbb0805202334/f66g1q5g4.jpg\" style=\"vertical-align: -17.0px;\"/>","text":"k = (1/4)"},{"id":"30D7358B35674EC0B548ADC87AF3B266","label":"B","html":"k = 16","text":"k = 16"},{"id":"22EFC16CCAC040B2BB97CAC0618F997B","label":"C","html":"k = 4","text":"k = 4"},{"id":"0174AAC0F5154ABF99175FCADAA38C83","label":"D","html":"Impossible","text":"Impossible"}],"correct_choice_ids":["22EFC16CCAC040B2BB97CAC0618F997B"],"correct_choice_indices":[2],"accepted_answers":[],"solution_html":"","solution_text":"","feedback_html":{},"images":[{"src":"assets/calct3bc/ppg/calct3bcbb0805202334/f66g1q5g1.jpg","alt":"  f(x) =  "},{"src":"assets/calct3bc/ppg/calct3bcbb0805202334/f66g1q5g2.jpg","alt":"{ (x) with superscript (2), kx,"},{"src":"assets/calct3bc/ppg/calct3bcbb0805202334/f66g1q5g3.jpg","alt":"if x ≤ 4if x > 4"},{"src":"assets/calct3bc/ppg/calct3bcbb0805202334/f66g1q5g4.jpg","alt":"(1/4)"}],"metadata":{"source_difficulty":"School","difficulty":null,"calculator":null,"estimated_seconds":90,"shuffle_choices":false,"review_status":"imported_unreviewed","math_format":"publisher_images_and_html"}},{"id":"ADAMS10-P00002-Q0072","source_object_id":"_10279458_1","bank_code":"ADAMS10","pool_id":"00002","pool_uid":"ADAMS10:00002","pool_title":"Chapter 01 Limits and Continuity","bank":{"code":"ADAMS10","title":"Calculus: A Complete Course, 10e","authors":"Adams, Essex","edition":"10e","isbn":"9780135732588","resource_isbn":"9780136835004","format":"Pearson test bank Blackboard QTI pool export + Word/TIF metadata"},"source":{"chapter":1,"chapter_title":"Limits and Continuity","section":"1.4","section_title":"Continuity","skill_number":null,"skill_title":"Continuity","publisher_format":"Pearson test bank Blackboard QTI pool export + Word/TIF metadata","original_question_number":72,"answer_key_text":"A"},"classification":{"ap_unit":1,"ap_unit_label":"Limits and Continuity","ap_topic":"1.13","ap_topic_title":"Removing Discontinuities","ap_scope":"ab_bc","course_scope":"AP Calculus AB/BC","alignment_confidence":"high","alignment_basis":"question_content_editorial_review","crosswalk_status":"editorially_reviewed_question_level","crosswalk_note":"Solves a parameter condition for a removable discontinuity.","framework":"AP Calculus Course and Exam Description, current Unit 1 topic framework"},"type":"mcq","prompt_html":"Let g(x) = <img alt=\"{table ( (((k) with superscript (2)- 2x /3-x)       if -∞  &lt; x &lt; 2)(12 if x = 2)(4x + k if 2 &lt; x &lt; ∞) )\" class=\"question-media\" decoding=\"async\" loading=\"lazy\" src=\"assets/adams10/ppg/ch10420211513/f1q72g1.jpg\" style=\"vertical-align: -36.0px;\"/>  <br/><br/>where k is a constant real number. If g has a removable discontinuity at x = 2, then k is equal to: ","prompt_text":"Let g(x) = {table ( (((k) with superscript (2)- 2x /3-x) if -∞ < x < 2)(12 if x = 2)(4x + k if 2 < x < ∞) ) where k is a constant real number. If g has a removable discontinuity at x = 2, then k is equal to:","choices":[{"id":"F2E1D9A12B414AE7B35E1A0017992BD9","label":"A","html":"-3 ","text":"-3"},{"id":"5A470883AA714BE0A916D37CC66684E5","label":"B","html":"±4","text":"±4"},{"id":"615769DACA2C44EBB5DAC3858648D130","label":"C","html":"3","text":"3"},{"id":"429E9EF0232743FFBFC609860479B415","label":"D","html":"4","text":"4"},{"id":"A257BEFA3836462F95EB32A3BA29CAE3","label":"E","html":"-4 or 3","text":"-4 or 3"}],"correct_choice_ids":["F2E1D9A12B414AE7B35E1A0017992BD9"],"correct_choice_indices":[0],"accepted_answers":[],"solution_html":"","solution_text":"","feedback_html":{},"images":[{"src":"assets/adams10/ppg/ch10420211513/f1q72g1.jpg","alt":"{table ( (((k) with superscript (2)- 2x /3-x)       if -∞  < x < 2)(12 if x = 2)(4x + k if 2 < x < ∞) )"}],"metadata":{"source_difficulty":3,"difficulty":3,"calculator":null,"estimated_seconds":140,"shuffle_choices":true,"review_status":"editorially_reviewed_teacher_approval_pending","math_format":"publisher_images_and_html"}},{"id":"ADAMS10-P00002-Q0074","source_object_id":"_10279460_1","bank_code":"ADAMS10","pool_id":"00002","pool_uid":"ADAMS10:00002","pool_title":"Chapter 01 Limits and Continuity","bank":{"code":"ADAMS10","title":"Calculus: A Complete Course, 10e","authors":"Adams, Essex","edition":"10e","isbn":"9780135732588","resource_isbn":"9780136835004","format":"Pearson test bank Blackboard QTI pool export + Word/TIF metadata"},"source":{"chapter":1,"chapter_title":"Limits and Continuity","section":"1.4","section_title":"Continuity","skill_number":null,"skill_title":"Continuity","publisher_format":"Pearson test bank Blackboard QTI pool export + Word/TIF metadata","original_question_number":74,"answer_key_text":"B"},"classification":{"ap_unit":1,"ap_unit_label":"Limits and Continuity","ap_topic":"1.13","ap_topic_title":"Removing Discontinuities","ap_scope":"ab_bc","course_scope":"AP Calculus AB/BC","alignment_confidence":"high","alignment_basis":"question_content_editorial_review","crosswalk_status":"editorially_reviewed_question_level","crosswalk_note":"Compares a hole with its continuous extension after defining the missing value.","framework":"AP Calculus Course and Exam Description, current Unit 1 topic framework"},"type":"mcq","prompt_html":"Is the function f(x) = <img alt=\"((x) with superscript (2) - 9/x - 3)\" class=\"question-media\" decoding=\"async\" loading=\"lazy\" src=\"assets/adams10/ppg/ch10420211513/f1q74g1.jpg\" style=\"vertical-align: -17.0px;\"/> discontinuous at any point of its domain? Would your answer change if we also define f(3) = 6?","prompt_text":"Is the function f(x) = ((x) with superscript (2) - 9/x - 3) discontinuous at any point of its domain? Would your answer change if we also define f(3) = 6?","choices":[{"id":"6DF136B6F7F64AA8BC2487847AF5F03E","label":"A","html":"yes, yes","text":"yes, yes"},{"id":"8C0121ABEE6649C6B9D0B9819F5A1874","label":"B","html":"no, no","text":"no, no"},{"id":"A797D80A3C4B4D1B9481682045AB671F","label":"C","html":"no, yes","text":"no, yes"},{"id":"0EDF2B1D2E784FC7A13B12AAC324C8CB","label":"D","html":"yes, no","text":"yes, no"},{"id":"B2E5BA8704EB49BDA98BCFED7C633FD2","label":"E","html":"none of the above","text":"none of the above"}],"correct_choice_ids":["6DF136B6F7F64AA8BC2487847AF5F03E"],"correct_choice_indices":[0],"accepted_answers":[],"solution_html":"","solution_text":"","feedback_html":{},"images":[{"src":"assets/adams10/ppg/ch10420211513/f1q74g1.jpg","alt":"((x) with superscript (2) - 9/x - 3)"}],"metadata":{"source_difficulty":2,"difficulty":2,"calculator":null,"estimated_seconds":115,"shuffle_choices":false,"review_status":"editorially_reviewed_teacher_approval_pending","math_format":"publisher_images_and_html"}},{"id":"ADAMS10-P00002-Q0075","source_object_id":"_10279461_1","bank_code":"ADAMS10","pool_id":"00002","pool_uid":"ADAMS10:00002","pool_title":"Chapter 01 Limits and Continuity","bank":{"code":"ADAMS10","title":"Calculus: A Complete Course, 10e","authors":"Adams, Essex","edition":"10e","isbn":"9780135732588","resource_isbn":"9780136835004","format":"Pearson test bank Blackboard QTI pool export + Word/TIF metadata"},"source":{"chapter":1,"chapter_title":"Limits and Continuity","section":"1.4","section_title":"Continuity","skill_number":null,"skill_title":"Continuity","publisher_format":"Pearson test bank Blackboard QTI pool export + Word/TIF metadata","original_question_number":75,"answer_key_text":"TRUE"},"classification":{"ap_unit":1,"ap_unit_label":"Limits and Continuity","ap_topic":"1.13","ap_topic_title":"Removing Discontinuities","ap_scope":"ab_bc","course_scope":"AP Calculus AB/BC","alignment_confidence":"high","alignment_basis":"question_content_editorial_review","crosswalk_status":"editorially_reviewed_question_level","crosswalk_note":"A removable hole is filled with the limiting value to create a continuous extension.","framework":"AP Calculus Course and Exam Description, current Unit 1 topic framework"},"type":"true_false","prompt_html":"If h(x) = <img alt=\"((x) with superscript (2) + 2x - 3/x - 1)\" class=\"question-media\" decoding=\"async\" loading=\"lazy\" src=\"assets/adams10/ppg/ch10420211513/f1q75g1.jpg\" style=\"vertical-align: -17.0px;\"/> if x ≠ 1 and h(1) = 4, then h is continuous at every x.","prompt_text":"If h(x) = ((x) with superscript (2) + 2x - 3/x - 1) if x ≠ 1 and h(1) = 4, then h is continuous at every x.","choices":[{"id":"true","label":"A","html":"true","text":"true"},{"id":"false","label":"B","html":"false","text":"false"}],"correct_choice_ids":["true"],"correct_choice_indices":[0],"accepted_answers":[],"solution_html":"","solution_text":"","feedback_html":{},"images":[{"src":"assets/adams10/ppg/ch10420211513/f1q75g1.jpg","alt":"((x) with superscript (2) + 2x - 3/x - 1)"}],"metadata":{"source_difficulty":2,"difficulty":2,"calculator":null,"estimated_seconds":70,"shuffle_choices":false,"review_status":"editorially_reviewed_teacher_approval_pending","math_format":"publisher_images_and_html"}},{"id":"ADAMS10-P00002-Q0077","source_object_id":"_10279463_1","bank_code":"ADAMS10","pool_id":"00002","pool_uid":"ADAMS10:00002","pool_title":"Chapter 01 Limits and Continuity","bank":{"code":"ADAMS10","title":"Calculus: A Complete Course, 10e","authors":"Adams, Essex","edition":"10e","isbn":"9780135732588","resource_isbn":"9780136835004","format":"Pearson test bank Blackboard QTI pool export + Word/TIF metadata"},"source":{"chapter":1,"chapter_title":"Limits and Continuity","section":"1.4","section_title":"Continuity","skill_number":null,"skill_title":"Continuity","publisher_format":"Pearson test bank Blackboard QTI pool export + Word/TIF metadata","original_question_number":77,"answer_key_text":"TRUE"},"classification":{"ap_unit":1,"ap_unit_label":"Limits and Continuity","ap_topic":"1.13","ap_topic_title":"Removing Discontinuities","ap_scope":"ab_bc","course_scope":"AP Calculus AB/BC","alignment_confidence":"high","alignment_basis":"question_content_editorial_review","crosswalk_status":"editorially_reviewed_question_level","crosswalk_note":"Characterizes when a finite limit permits a continuous extension.","framework":"AP Calculus Course and Exam Description, current Unit 1 topic framework"},"type":"true_false","prompt_html":"If <img alt=\"(x → c) is under (lim)\" class=\"question-media\" decoding=\"async\" loading=\"lazy\" src=\"assets/adams10/ppg/ch10420211513/f1q77g1.jpg\" style=\"vertical-align: -21.0px;\"/>f(x) exists and is finite, then either f is continuous at x = c or f has a continuous extension to x = c.","prompt_text":"If (x → c) is under (lim) f(x) exists and is finite, then either f is continuous at x = c or f has a continuous extension to x = c.","choices":[{"id":"true","label":"A","html":"true","text":"true"},{"id":"false","label":"B","html":"false","text":"false"}],"correct_choice_ids":["true"],"correct_choice_indices":[0],"accepted_answers":[],"solution_html":"","solution_text":"","feedback_html":{},"images":[{"src":"assets/adams10/ppg/ch10420211513/f1q77g1.jpg","alt":"(x → c) is under (lim)"}],"metadata":{"source_difficulty":1,"difficulty":1,"calculator":null,"estimated_seconds":45,"shuffle_choices":false,"review_status":"editorially_reviewed_teacher_approval_pending","math_format":"publisher_images_and_html"}}]}